{"stats":{"minecraft:picked_up":{"minecraft:stone_axe":2,"minecraft:gold_ingot":7,"minecraft:chest":6},"minecraft:custom":{"minecraft:time_since_rest":888,"minecraft:open_chest":8,"minecraft:play_one_minute":17399,"minecraft:crouch_one_cm":2729,"minecraft:open_enderchest":1,"minecraft:sprint_one_cm":86322,"minecraft:walk_one_cm":18319,"minecraft:damage_taken":3455,"minecraft:deaths":14,"minecraft:sneak_time":1083,"minecraft:trigger_trapped_chest":1,"minecraft:walk_under_water_one_cm":1171,"minecraft:drop":2,"minecraft:jump":467,"minecraft:damage_dealt":547,"minecraft:leave_game":1,"minecraft:walk_on_water_one_cm":684,"minecraft:time_since_death":844,"minecraft:climb_one_cm":832,"minecraft:swim_one_cm":3654,"minecraft:fall_one_cm":66722,"minecraft:fly_one_cm":124697},"minecraft:dropped":{"minecraft:stone_axe":2},"minecraft:used":{"minecraft:stone_axe":16},"minecraft:mined":{"minecraft:chest":5},"minecraft:killed_by":{"minecraft:player":6}},"DataVersion":2586}